hedging_gym/__init__.py
hedging_gym/math.py
hedging_gym/py.typed
hedging_gym/base/__init__.py
hedging_gym/base/call_env.py
hedging_gym/base/spread_env.py
hedging_gym/envs/__init__.py
hedging_gym/envs/bs_env.py
hedging_gym/envs/heston_env.py
hedging_gym/envs/margrabe_env.py
hedging_gym/utils/__init__.py
hedging_gym/utils/env_checker.py
hedging_gym-0.0.2.dist-info/METADATA
hedging_gym-0.0.2.dist-info/WHEEL
hedging_gym-0.0.2.dist-info/top_level.txt
hedging_gym-0.0.2.dist-info/RECORD
