Metadata-Version: 2.1
Name: hedging-gym
Version: 0.0.2
Summary: HedgingGym is a reinforcement learning environment for training and testing hedging strategies.
Author-email: Paolo D'Elia <paolo.delia99@gmail.com>
Classifier: Programming Language :: Python :: 3
Classifier: License :: OSI Approved :: MIT License
Classifier: Operating System :: OS Independent
Classifier: Topic :: Scientific/Engineering :: Mathematics
Classifier: Topic :: Software Development :: Libraries :: Python Modules
Classifier: Intended Audience :: Financial and Insurance Industry
Classifier: Intended Audience :: Education
Classifier: Intended Audience :: Developers
Requires-Python: >=3.10
Requires-Dist: gymnasium ==0.29.1
Requires-Dist: numpy ==1.26.4
Requires-Dist: JaxFin ==0.3.3
Requires-Dist: jax ==0.4.23
